thestockslib/__init__.py
thestockslib-0.1.0.dist-info/METADATA
thestockslib-0.1.0.dist-info/WHEEL
thestockslib-0.1.0.dist-info/top_level.txt
thestockslib-0.1.0.dist-info/RECORD
