Metadata-Version: 2.1
Name: thestockslib
Version: 0.1.0
Summary: A simple stocks package
Home-page: https://github.com/auino/thestockslib
Author: Enrico Cambiaso
Author-email: enrico.cambiaso@gmail.com
License: UNKNOWN
Platform: UNKNOWN
Classifier: Programming Language :: Python :: 3
Classifier: License :: OSI Approved :: MIT License
Classifier: Operating System :: OS Independent
Requires-Python: >=3.6
